aves/__init__.py
aves/__main__.py
aves/aves.py
aves/aves_onnx.py
aves/aves_transformers.py
aves/download_models.py
aves/py.typed
aves/utils.py
esp_aves-1.0.0.dist-info/licenses/LICENSE
esp_aves-1.0.0.dist-info/METADATA
esp_aves-1.0.0.dist-info/WHEEL
esp_aves-1.0.0.dist-info/entry_points.txt
esp_aves-1.0.0.dist-info/top_level.txt
esp_aves-1.0.0.dist-info/RECORD
