Metadata-Version: 2.4
Name: esp-aves
Version: 1.0.0
Summary: AVES package for audio feature extraction
Author-email: Masato Hagiwara <masato@earthspecies.org>, Maddie Cusimano <maddie@earthspecies.org>, Gagan Narula <gagan@earthspecies.org>
License: MIT
Project-URL: Homepage, https://github.com/earthspecies/aves
Project-URL: Bug Tracker, https://github.com/earthspecies/aves/issues
Keywords: audio,machine learning,animal sounds,feature extraction
Classifier: Development Status :: 4 - Beta
Classifier: Intended Audience :: Science/Research
Classifier: License :: OSI Approved :: MIT License
Classifier: Programming Language :: Python :: 3
Classifier: Programming Language :: Python :: 3.10
Classifier: Topic :: Scientific/Engineering :: Artificial Intelligence
Classifier: Topic :: Multimedia :: Sound/Audio :: Analysis
Requires-Python: >=3.10
License-File: LICENSE
Requires-Dist: torch>=2.0.0
Requires-Dist: torchaudio>=2.0.0
Requires-Dist: soundfile>=0.13.0
Requires-Dist: pytest>=8.3.4
Requires-Dist: onnxruntime>=1.20.1
Dynamic: license-file
